dude/__init__.py
dude/smack_talker.py
smack_talker_pkg_msmith_pdc-1.0.0.dist-info/LICENSE.txt
smack_talker_pkg_msmith_pdc-1.0.0.dist-info/METADATA
smack_talker_pkg_msmith_pdc-1.0.0.dist-info/WHEEL
smack_talker_pkg_msmith_pdc-1.0.0.dist-info/top_level.txt
smack_talker_pkg_msmith_pdc-1.0.0.dist-info/RECORD
